inspirobot/__init__.py
inspirobot/error.py
inspirobot/flow.py
inspirobot/generate.py
inspiro-0.0.2.dist-info/LICENSE
inspiro-0.0.2.dist-info/METADATA
inspiro-0.0.2.dist-info/WHEEL
inspiro-0.0.2.dist-info/top_level.txt
inspiro-0.0.2.dist-info/RECORD
