Metadata-Version: 2.1
Name: inspiro
Version: 0.0.2
Summary: Python3 API wrapper for InspiroBot
Home-page: https://github.com/samhdev/inspiro
Author: SamHDev
Author-email: sam.fucked.up@samh.dev
License: UNKNOWN
Platform: UNKNOWN
Classifier: Programming Language :: Python :: 3
Classifier: License :: OSI Approved :: MIT License
Classifier: Operating System :: OS Independent
Requires-Python: >=3.5
